pyaliner/__init__.py
pyaliner/align.py
pyaliner/autoalign.py
pyaliner/cli.py
pyaliner/compare.py
pyaliner/display.py
pyaliner/examples.py
pyaliner-0.1.2.dist-info/LICENSE
pyaliner-0.1.2.dist-info/METADATA
pyaliner-0.1.2.dist-info/WHEEL
pyaliner-0.1.2.dist-info/top_level.txt
pyaliner-0.1.2.dist-info/RECORD
